qrng/__init__.py
qrng-0.1.2.dist-info/LICENSE
qrng-0.1.2.dist-info/METADATA
qrng-0.1.2.dist-info/WHEEL
qrng-0.1.2.dist-info/top_level.txt
qrng-0.1.2.dist-info/RECORD
