Metadata-Version: 2.1
Name: qrng
Version: 0.1.2
Summary: A Quantum Random Number Generator using IBM's Qiskit
Home-page: https://github.com/ozanerhansha/qRNG
Author: Ozaner Hansha
Author-email: ozanerhansha@gmail.com
License: UNKNOWN
Platform: UNKNOWN
Classifier: Programming Language :: Python :: 3
Classifier: License :: OSI Approved :: MIT License
Classifier: Operating System :: OS Independent
